{
	"author" : "Joel Simon",
	"primer_groups" : [
		{
			"name" : "iGH-c",
			"forwards" : [
				"TAAAAGGTGTCCAGTGT", "TTAAAGCTGTCCAGTGT", "TAAGAGGTGTCCAGTGT",
				"TAGAAGGTGTCCAGTGT", "TTCTCCAAGGAGTCTGT", "ATGAAACATCTGTGGTTCTT",
				"TACAAGGTGTCCAGTGT", "ATGAAACACCTGTGGTTCTT"
			],
			"reverses" : ["GTTCGGGGAAGTAGTCCTTGAC"]
		},
		{
			"name" : "iGH-d",
			"forwards" : [
				"ATGGACTGGATTTGGAGGAT", "GCTATTTTTAAAGGTGTCCAGTGT", "ATGTCTGTCTCCTTCCTCATC", 
				"CCTCCACAGTGAGAGTCTG", "ATGAAGCACCTGTGGTTCTT", "ATGAAACACCTGTGGTTCTTCC",
				"ATGGACTGGACCTGGAGAAT", "GGTTCCTCTTTGTGGTGGC", "ATGGACTGGACCTGGAGGAT"
			],
			"reverses" : ["GTTCGGGGAAGTAGTCCTTGAC"]
		},
		{
			"name" : "iGH-e",
			"forwards" : [
				"ATGGACTGGACCTGGAGCAT", "AGGTTCCTCTTTGTGGTGGCAG",
				"ATGGACTGGACCTGGAGGGT", "GGCAGCAGCAACAGGTGCCCA"
			],
			"reverses" : ["GTTCGGGGAAGTAGTCCTTGAC"]
		}
	]
}